llama_index/indices/managed/bge_m3/__init__.py
llama_index/indices/managed/bge_m3/base.py
llama_index/indices/managed/bge_m3/retriever.py
llama_index_indices_managed_bge_m3-0.6.1.dist-info/METADATA
llama_index_indices_managed_bge_m3-0.6.1.dist-info/WHEEL
llama_index_indices_managed_bge_m3-0.6.1.dist-info/licenses/LICENSE
llama_index_indices_managed_bge_m3-0.6.1.dist-info/RECORD
