Metadata-Version: 2.4
Name: llama-index-indices-managed-bge-m3
Version: 0.6.1
Summary: llama-index managed indices bge-m3 integration
Author-email: Panuthep Tasawong <panuthep.t_s20@vistec.ac.th>
License-Expression: MIT
License-File: LICENSE
Requires-Python: <4.0,>=3.9
Requires-Dist: flagembedding>=1.2.11
Requires-Dist: llama-index-core<0.15,>=0.13.0
Requires-Dist: peft>=0.12.0
